sindmap/__init__.py
sindmap/drivable_area.py
sindmap/map_api.py
sindmap/pedestrian_crossing.py
sindmap/intersection/__init__.py
sindmap/intersection/intersection.py
sindmap/lane/__init__.py
sindmap/lane/lane_segment.py
sindmap/stretch/__init__.py
sindmap/stretch/stretch.py
sindmap/utils/__init__.py
sindmap/utils/map_primitives.py
sindmap/utils/typing.py
abcac-0.0.1.dist-info/LICENSE
abcac-0.0.1.dist-info/LICENSE.txt
abcac-0.0.1.dist-info/METADATA
abcac-0.0.1.dist-info/WHEEL
abcac-0.0.1.dist-info/top_level.txt
abcac-0.0.1.dist-info/RECORD
