Metadata-Version: 2.1
Name: abcac
Version: 0.0.1
Summary: Map api for SinD dataset
Author: Helios1208
Author-email: cly020329@gmail.com
License: Apache 3.0
Requires-Python: >=3.8
License-File: LICENSE
License-File: LICENSE.txt
Requires-Dist: numpy
Requires-Dist: pyyaml
